COPYING.txt
MANIFEST.in
README.rst
setup.py
atomac/AXCallbacks.py
atomac/AXClasses.py
atomac/AXKeyCodeConstants.py
atomac/AXKeyboard.py
atomac/Clipboard.py
atomac/Prefs.py
atomac/__init__.py
atomac/version.py
atomac.egg-info/PKG-INFO
atomac.egg-info/SOURCES.txt
atomac.egg-info/dependency_links.txt
atomac.egg-info/entry_points.txt
atomac.egg-info/top_level.txt
atomac/_a11y/a11ymodule.c
atomac/_a11y/axlib.c
atomac/_a11y/axlib.h
atomac/_a11y/conversion.c
atomac/_a11y/conversion.h
atomac/ldtp/__init__.py
atomac/ldtp/client.py
atomac/ldtp/client_exception.py
atomac/ldtp/log.py
atomac/ldtp/state.py
atomac/ldtpd/__init__.py
atomac/ldtpd/combo_box.py
atomac/ldtpd/constants.py
atomac/ldtpd/core.py
atomac/ldtpd/generic.py
atomac/ldtpd/keypress_actions.py
atomac/ldtpd/menu.py
atomac/ldtpd/mouse.py
atomac/ldtpd/page_tab_list.py
atomac/ldtpd/server_exception.py
atomac/ldtpd/table.py
atomac/ldtpd/test.py
atomac/ldtpd/text.py
atomac/ldtpd/utils.py
atomac/ldtpd/value.py