Metadata-Version: 1.0
Name: atomac
Version: 1.1.0
Summary: Automated Testing on Mac - test GUI applications written in Cocoa by using Apple's Accessibility API
Home-page: http://pyatom.com
Author: The ATOMac Team
Author-email: pyatom-dev@lists.pyatom.com
License: GPLv2
Platform: UNKNOWN
Classifier: Development Status :: 5 - Production/Stable
Classifier: Environment :: MacOS X :: Cocoa
Classifier: License :: OSI Approved :: GNU General Public License (GPL)
Classifier: Topic :: Software Development :: Quality Assurance
Classifier: Topic :: Software Development :: Testing
